<?xml version="1.0" encoding="utf-8"?>

<ModMetaData>
	<name>[RH] Faction: The Ghosts (1.0)</name>
	<author>Chicken Plucker</author>
	<supportedVersions><li>1.0</li></supportedVersions>
	<description>Officially known as Task Force: STALKER. 
	
A mysterious group of masked warriors arrive in this Rim planet with no official ties to any country, government or organization. They're Ghosts, fighting for something that can't be killed.






Credits to:
Ods and BajtMe - For help with awesome apparel textures
Jecrell, Jdalt40, dninemfive and Spdskatr - For C# coding assistance and patches</description>
</ModMetaData>